flask_authlib/__init__.py
flask_authlib/main.py
flask_authlib/schemas.py
flask_authlib/settings.py
flask_authlib/templates.zip
flask_authlib/utils.py
flask_authlib/views.py
flask_authlib/database/__init__.py
flask_authlib/database/models.py
flask_authlib/jwt/__init__.py
flask_authlib/jwt/exceptions.py
flask_authlib/jwt/main.py
flask_authlib/jwt/utils.py
flask_authlib/jwt/views.py
Flask_Authlib-1.6.0.dist-info/LICENSE
Flask_Authlib-1.6.0.dist-info/METADATA
Flask_Authlib-1.6.0.dist-info/WHEEL
Flask_Authlib-1.6.0.dist-info/top_level.txt
Flask_Authlib-1.6.0.dist-info/RECORD
