Metadata-Version: 2.1
Name: Flask-Authlib
Version: 1.6.0
Summary: Authentication library for Flask Web Framework 
Home-page: https://github.com/AbduazizZiyodov/flask-authlib
Author: Abduaziz Ziyodov
Author-email: abduaziz.ziyodov@mail.ru
License: MIT
Platform: any
Classifier: License :: OSI Approved :: MIT License
Classifier: Operating System :: OS Independent
Classifier: Programming Language :: Python :: 3
Classifier: Programming Language :: Python :: 3.8
Classifier: Programming Language :: Python :: Implementation :: CPython
Classifier: Environment :: Web Environment
License-File: LICENSE
